[{"pk": 1, "model": "app_emergencia.emergencia", "fields": {"destino": null, "hora_ingreso": "2013-07-26T02:54:09", "paciente": 1, "hora_ingresoReal": "2013-07-26T02:54:50.089", "hora_egresoReal": null, "egreso": null, "responsable": 2, "hora_egreso": null, "ingreso": 2}}, {"pk": 2, "model": "app_emergencia.emergencia", "fields": {"destino": null, "hora_ingreso": "2013-07-26T02:54:56", "paciente": 2, "hora_ingresoReal": "2013-07-26T02:55:40.206", "hora_egresoReal": null, "egreso": null, "responsable": 2, "hora_egreso": null, "ingreso": 2}}, {"pk": 3, "model": "app_emergencia.emergencia", "fields": {"destino": null, "hora_ingreso": "2013-07-26T02:55:47", "paciente": 3, "hora_ingresoReal": "2013-07-26T02:56:46.675", "hora_egresoReal": null, "egreso": null, "responsable": 2, "hora_egreso": null, "ingreso": 2}}, {"pk": 4, "model": "app_emergencia.emergencia", "fields": {"destino": null, "hora_ingreso": "2013-07-26T15:07:59", "paciente": 4, "hora_ingresoReal": "2013-07-26T15:08:46.657", "hora_egresoReal": null, "egreso": null, "responsable": 2, "hora_egreso": null, "ingreso": 2}}, {"pk": 5, "model": "app_emergencia.emergencia", "fields": {"destino": null, "hora_ingreso": "2013-08-01T10:24:44", "paciente": 5, "hora_ingresoReal": "2013-08-01T10:26:06.004", "hora_egresoReal": null, "egreso": null, "responsable": 3, "hora_egreso": null, "ingreso": 3}}, {"pk": 6, "model": "app_emergencia.emergencia", "fields": {"destino": null, "hora_ingreso": "2013-08-01T10:26:27", "paciente": 6, "hora_ingresoReal": "2013-08-01T10:27:54.913", "hora_egresoReal": null, "egreso": null, "responsable": 3, "hora_egreso": null, "ingreso": 3}}, {"pk": 7, "model": "app_emergencia.emergencia", "fields": {"destino": null, "hora_ingreso": "2013-08-01T10:28:14", "paciente": 7, "hora_ingresoReal": "2013-08-01T10:35:59.566", "hora_egresoReal": null, "egreso": null, "responsable": 3, "hora_egreso": null, "ingreso": 3}}, {"pk": 8, "model": "app_emergencia.emergencia", "fields": {"destino": null, "hora_ingreso": "2013-08-01T10:36:53", "paciente": 8, "hora_ingresoReal": "2013-08-01T10:38:09.580", "hora_egresoReal": null, "egreso": null, "responsable": 3, "hora_egreso": null, "ingreso": 3}}, {"pk": 9, "model": "app_emergencia.emergencia", "fields": {"destino": null, "hora_ingreso": "2013-08-01T10:39:59", "paciente": 9, "hora_ingresoReal": "2013-08-01T10:41:37.500", "hora_egresoReal": null, "egreso": null, "responsable": 3, "hora_egreso": null, "ingreso": 3}}, {"pk": 10, "model": "app_emergencia.emergencia", "fields": {"destino": null, "hora_ingreso": "2013-08-01T10:41:45", "paciente": 10, "hora_ingresoReal": "2013-08-01T10:43:29.602", "hora_egresoReal": null, "egreso": null, "responsable": 3, "hora_egreso": null, "ingreso": 3}}]
